cbse_results_scraper/__init__.py
cbse_results_scraper/app.py
cbse_results_scraper/constants.py
CBSE_Results_Scraper-1.2.9.dist-info/LICENSE.txt
CBSE_Results_Scraper-1.2.9.dist-info/METADATA
CBSE_Results_Scraper-1.2.9.dist-info/WHEEL
CBSE_Results_Scraper-1.2.9.dist-info/entry_points.txt
CBSE_Results_Scraper-1.2.9.dist-info/top_level.txt
CBSE_Results_Scraper-1.2.9.dist-info/RECORD
